README.rst
setup.cfg
setup.py
CheKnife/__init__.py
CheKnife/dynamic_import.py
CheKnife/errors.py
CheKnife/files.py
CheKnife/generators.py
CheKnife/hashing.py
CheKnife/json.py
CheKnife/lists.py
CheKnife/logs.py
CheKnife/network.py
CheKnife/os.py
CheKnife/paths.py
CheKnife/pki.py
CheKnife/prompts.py
CheKnife/security.py
CheKnife/ssl.py
CheKnife/text.py
CheKnife/time.py
CheKnife/version.py
CheKnife.egg-info/PKG-INFO
CheKnife.egg-info/SOURCES.txt
CheKnife.egg-info/dependency_links.txt
CheKnife.egg-info/requires.txt
CheKnife.egg-info/top_level.txt
CheKnife/django/__init__.py
CheKnife/django/choiceutils.py
CheKnife/django/queryset_iterators.py
CheKnife/networking/__init__.py
CheKnife/networking/speedtest.py
CheKnife/networking/speedtest_log_print.py
tests/__init__.py
tests/test_CheKnife.py
tests/test_files.py
tests/test_network.py
tests/test_pki.py
tests/test_ssl.py
tests/aux_data/__init__.py
tests/aux_data/aux_variables.py