Metadata-Version: 1.1
Name: CheKnife
Version: 0.0.8
Summary: Python Utilities
Home-page: https://git.herrerosolis.com/Misc/CheKnife
Author: Rafael Herrero Solis
Author-email: rafahsolis@hotmail.com
License: MIT license
Download-URL: https://git.herrerosolis.com/Misc/CheKnife/-/archive/v0.0.8/CheKnife-v0.0.8.tar.gz
Keywords: CheKnife,Swiss,Army,Knife,Swiss Army Knife
Platform: UNKNOWN
Classifier: License :: OSI Approved :: MIT License
Classifier: Development Status :: 3 - Alpha
Classifier: License :: OSI Approved :: Apache Software License
Classifier: Programming Language :: Python :: 3.6
